komle_witslm_client/WMLS.WSDL
komle_witslm_client/__init__.py
komle_witslm_client/soap_client.py
komle_witslm_client/uom_converter.py
komle_witslm_client/utils.py
komle_witslm_client/witsmlUnitDict.xml
komle_witslm_client/bindings/__init__.py
komle_witslm_client/bindings/uom.py
komle_witslm_client/bindings/v1311/__init__.py
komle_witslm_client/bindings/v1311/witsml.py
komle_witslm_client/bindings/v1311/api/__init__.py
komle_witslm_client/bindings/v1311/api/witsml.py
komle_witslm_client/bindings/v1410/__init__.py
komle_witslm_client/bindings/v1410/api/__init__.py
komle_witslm_client/bindings/v1410/api/witsml.py
komle_witslm_client/bindings/v1410/delete/__init__.py
komle_witslm_client/bindings/v1410/delete/_abs.py
komle_witslm_client/bindings/v1410/delete/_gco.py
komle_witslm_client/bindings/v1410/delete/_gmd.py
komle_witslm_client/bindings/v1410/delete/_gml.py
komle_witslm_client/bindings/v1410/delete/_gsr.py
komle_witslm_client/bindings/v1410/delete/_gss.py
komle_witslm_client/bindings/v1410/delete/_gts.py
komle_witslm_client/bindings/v1410/delete/_nsgroup.py
komle_witslm_client/bindings/v1410/delete/_xlink.py
komle_witslm_client/bindings/v1410/delete/witsml.py
komle_witslm_client/bindings/v1410/read/__init__.py
komle_witslm_client/bindings/v1410/read/_abs.py
komle_witslm_client/bindings/v1410/read/_gco.py
komle_witslm_client/bindings/v1410/read/_gmd.py
komle_witslm_client/bindings/v1410/read/_gml.py
komle_witslm_client/bindings/v1410/read/_gsr.py
komle_witslm_client/bindings/v1410/read/_gss.py
komle_witslm_client/bindings/v1410/read/_gts.py
komle_witslm_client/bindings/v1410/read/_nsgroup.py
komle_witslm_client/bindings/v1410/read/_xlink.py
komle_witslm_client/bindings/v1410/read/witsml.py
komle_witslm_client/bindings/v1410/update/__init__.py
komle_witslm_client/bindings/v1410/update/_abs.py
komle_witslm_client/bindings/v1410/update/_gco.py
komle_witslm_client/bindings/v1410/update/_gmd.py
komle_witslm_client/bindings/v1410/update/_gml.py
komle_witslm_client-0.3.4.2.dist-info/LICENSE
komle_witslm_client-0.3.4.2.dist-info/METADATA
komle_witslm_client-0.3.4.2.dist-info/WHEEL
komle_witslm_client-0.3.4.2.dist-info/top_level.txt
komle_witslm_client-0.3.4.2.dist-info/RECORD
