Metadata-Version: 2.1
Name: komle-witslm-client
Version: 0.3.4.2
Summary: A python library to help with WITSML v1.3.1.1, v1.4.1.0, v1.4.1.1 and v2.0
Home-page: https://github.com/nqtung/komle-witsml-client
Author: Tung Nguyen
Author-email: tungnq@gmail.com
License: Apache-2.0 License
Keywords: python,soap-client,witsml
Requires-Python: >=3.9
License-File: LICENSE
Requires-Dist: suds-py3 (==1.4.5.0)
Requires-Dist: PyXB-X (==1.2.6)
Requires-Dist: requests (==2.27.1)
Requires-Dist: xmltodict (==0.12.0)
